a2conn/__init__.py
a2conn/mod1.py
a2conn/mod2.py
a2conn/zebra.py
a2conn-0.1.0.dist-info/METADATA
a2conn-0.1.0.dist-info/WHEEL
a2conn-0.1.0.dist-info/entry_points.txt
a2conn-0.1.0.dist-info/top_level.txt
a2conn-0.1.0.dist-info/RECORD
